AUTHORS.md
CHANGES.md
LICENSE
MANIFEST.in
README.md
requirements.txt
setup.py
getch/__init__.py
getch/getch.py
getch/pause.py
py_getch.egg-info/PKG-INFO
py_getch.egg-info/SOURCES.txt
py_getch.egg-info/dependency_links.txt
py_getch.egg-info/not-zip-safe
py_getch.egg-info/top_level.txt