Metadata-Version: 1.0
Name: py-getch
Version: 1.0.0
Summary: Portable getch() for Python.
Home-page: https://github.com/joeyespo/py-getch
Author: Joe Esposito
Author-email: joe@joeyespo.com
License: MIT
Platform: any
